[{"Date":"","Lunch":"","Snack":""},{"Date":"Date","Lunch":"Lunch","Snack":"Snack"},{"Date":"11/1/2016","Lunch":"Plain Pilau, Egg Curry and Tomato Chutney","Snack":""},{"Date":"11/2/2016","Lunch":"Rice, Dal, Chicken Curry, (For Veg. Kofta \u0026 Curd, Lalmohon) Pickle","Snack":"Alu Pakora"},{"Date":"11/3/2016","Lunch":"Rice, Daal, Mix Veg., Salad, Tomato Chutney","Snack":"Noodles Soup"},{"Date":"11/4/2016","Lunch":"Plain Pilau, Egg Curry, (For Veg. Mushroom) \u0026 Chutney, Papad","Snack":"Paratha \u0026 Chutney"},{"Date":"11/7/2016","Lunch":"Rice, Dal, Mushroom Curry, Tomato Chutney","Snack":"Sadheko Aloo \u0026 Bhujiya"},{"Date":"11/8/2016","Lunch":"Rice, Kidney Beans, Green, Nutrela Chutney, Salad","Snack":"Plain Khir"},{"Date":"11/9/2016","Lunch":"Rice, Chicken Fry, (Only For Veg. Paneer \u0026 Curd) Pickle ","Snack":"Fruits"},{"Date":"11/10/2016","Lunch":"Rice, Mixed Beans, Fish Chutney, (For Veg. Tomato Chutney \u0026 Curd)","Snack":"Roti \u0026 Curry"},{"Date":"11/11/2016","Lunch":"Rice, Egg Curry, (For Veg. Cauliflower Curry), Papad, Pickle ","Snack":"Veg. MOMO"},{"Date":"11/14/2016","Lunch":"Rice, Dal, Mixed Veg., Tomato Chutney, Papad","Snack":"Spring Roll"},{"Date":"11/15/2016","Lunch":"Rice, Pea \u0026 Potato, Salad, Chutney","Snack":"French Toast"},{"Date":"11/16/2016","Lunch":"Rice, Dal, Chicken,(For Veg. Mushroom Curry \u0026 Curd), Pickle","Snack":"Muffin and Chips"},{"Date":"11/17/2016","Lunch":"Coconut Pilau, Mixed Beans, Brinjal \u0026 Potato Curry, Tomato Chutney","Snack":"Chapati \u0026 Chutney"},{"Date":"11/18/2016","Lunch":"Mixed Pilau, Egg Curry (For Veg. Cofta), Pickle","Snack":"Samosa "},{"Date":"11/21/2016","Lunch":"Plain Pilau, White Beans, Sweet Chutney, Salad","Snack":"Sukka Roti \u0026 Curry"},{"Date":"11/22/2016","Lunch":"Rice, Mung Dal, Mushroom Curry, Pickle","Snack":"Finger Chips"},{"Date":"11/23/2016","Lunch":"Rice, Dal, Chicken,(Only For Veg. Broccoli \u0026 Curd), Pickel","Snack":"Alu Pakora "},{"Date":"11/24/2016","Lunch":"Rice, Black Dal, Bitter Gourd Chutney, Curd, Papad  ","Snack":"Bhatura \u0026 Pea Curry"},{"Date":"11/25/2016","Lunch":"Rice, Egg Curry, (Only for Veg. Brinjal Pakora, Curd), Salad, Pickle","Snack":"Veg. Burger"},{"Date":"11/28/2016","Lunch":"Rice, Lady's Finger, Kidney Beans, Nutrela Chutney","Snack":"Mixed Khir"},{"Date":"11/29/2016","Lunch":"Rice, Mung Dal, Mushroom Curry, Pickle","Snack":"Veg. Sandwich"},{"Date":"11/30/2016","Lunch":"Rice, Dal, Chicken,(Only For Veg. Broccoli \u0026 Curd), Pickel","Snack":"Thukpa"},{"Date":"12/1/2016","Lunch":"Rice, Green, Bitter Gourd Chutney, Curd, Papad  ","Snack":"Pasta"},{"Date":"12/2/2016","Lunch":"Rice, Egg Curry, (Only for Veg. Brinjal Pakora, Curd), Salad, Pickle","Snack":"Sel Roti \u0026 Chutney"}]